[{"id":1,"posX":10,"posY":10,"width":25,"height":25,"zIndex":0,"source":"FacialHair 1.npg","filter":""},{"id":2,"posX":10,"posY":10,"width":25,"height":25,"zIndex":0,"source":"FacialHair 2.npg","filter":""},{"id":3,"posX":10,"posY":10,"width":25,"height":25,"zIndex":0,"source":"FacialHair 3.npg","filter":""},{"id":4,"posX":10,"posY":10,"width":25,"height":25,"zIndex":0,"source":"FacialHair 4.npg","filter":""},{"id":5,"posX":10,"posY":10,"width":25,"height":25,"zIndex":0,"source":"FacialHair 5.npg","filter":""},{"id":6,"posX":10,"posY":10,"width":25,"height":25,"zIndex":0,"source":"FacialHair 6.npg","filter":""},{"id":7,"posX":10,"posY":10,"width":25,"height":25,"zIndex":0,"source":"FacialHair 7.npg","filter":""},{"id":8,"posX":10,"posY":10,"width":25,"height":25,"zIndex":0,"source":"FacialHair 8.npg","filter":""},{"id":9,"posX":10,"posY":10,"width":25,"height":25,"zIndex":0,"source":"FacialHair 9.npg","filter":""},{"id":10,"posX":10,"posY":10,"width":25,"height":25,"zIndex":0,"source":"FacialHair 10.npg","filter":""},{"id":11,"posX":10,"posY":10,"width":25,"height":25,"zIndex":0,"source":"FacialHair 11.npg","filter":""},{"id":12,"posX":10,"posY":10,"width":25,"height":25,"zIndex":0,"source":"FacialHair 12.npg","filter":""},{"id":13,"posX":10,"posY":10,"width":25,"height":25,"zIndex":0,"source":"FacialHair 13.npg","filter":""},{"id":14,"posX":10,"posY":10,"width":25,"height":25,"zIndex":0,"source":"FacialHair 14.npg","filter":""},{"id":15,"posX":10,"posY":10,"width":25,"height":25,"zIndex":0,"source":"FacialHair 15.npg","filter":""},{"id":16,"posX":10,"posY":10,"width":25,"height":25,"zIndex":0,"source":"FacialHair 16.npg","filter":""},{"id":17,"posX":10,"posY":10,"width":25,"height":25,"zIndex":0,"source":"FacialHair 17.npg","filter":""},{"id":18,"posX":10,"posY":10,"width":25,"height":25,"zIndex":0,"source":"FacialHair 18.npg","filter":""},{"id":19,"posX":10,"posY":10,"width":25,"height":25,"zIndex":0,"source":"FacialHair 19.npg","filter":""}]